byro/__init__.py
byro/__main__.py
byro/celery_app.py
byro/settings.py
byro/urls.py
byro/wsgi.py
byro/bookkeeping/__init__.py
byro/bookkeeping/apps.py
byro/bookkeeping/forms.py
byro/bookkeeping/signals.py
byro/bookkeeping/special_accounts.py
byro/bookkeeping/migrations/0001_initial.py
byro/bookkeeping/migrations/0002_auto_20170812_1109.py
byro/bookkeeping/migrations/0003_auto_20170812_1237.py
byro/bookkeeping/migrations/0004_auto_20170919_1832.py
byro/bookkeeping/migrations/0005_auto_20170919_1832.py
byro/bookkeeping/migrations/0006_remove_account_member.py
byro/bookkeeping/migrations/0007_auto_20171206_1919.py
byro/bookkeeping/migrations/0008_auto_20180111_1807.py
byro/bookkeeping/migrations/0009_realtransactionsource_state.py
byro/bookkeeping/migrations/0010_auto_20180113_1500.py
byro/bookkeeping/migrations/0011_auto_20180303_1745.py
byro/bookkeeping/migrations/0012_auto_20180617_1926.py
byro/bookkeeping/migrations/0013_new_data_model.py
byro/bookkeeping/migrations/0014_auto_20180707_1410.py
byro/bookkeeping/migrations/0015_auto_20180707_1522.py
byro/bookkeeping/migrations/0016_auto_20181013_1611.py
byro/bookkeeping/migrations/0017_auto_20200818_2002.py
byro/bookkeeping/migrations/__init__.py
byro/bookkeeping/models/__init__.py
byro/bookkeeping/models/account.py
byro/bookkeeping/models/real_transaction.py
byro/bookkeeping/models/transaction.py
byro/common/apps.py
byro/common/console.py
byro/common/context_processors.py
byro/common/middleware.py
byro/common/signals.py
byro/common/urls.py
byro/common/utils.py
byro/common/views.py
byro/common/formats/__init__.py
byro/common/formats/en/__init__.py
byro/common/formats/en/formats.py
byro/common/forms/__init__.py
byro/common/forms/configuration.py
byro/common/forms/registration.py
byro/common/management/__init__.py
byro/common/management/commands/__init__.py
byro/common/management/commands/export_logchain.py
byro/common/management/commands/make_testdata.py
byro/common/management/commands/runperiodic.py
byro-2023.1.0.dist-info/METADATA
byro-2023.1.0.dist-info/WHEEL
byro-2023.1.0.dist-info/top_level.txt
byro-2023.1.0.dist-info/RECORD
