Metadata-Version: 2.1
Name: byro
Version: 2023.1.0
Summary: Membership and fees management for associations, clubs and groups
Home-page: https://byro.cloud
Author: Tobias Kunze
Author-email: r@rixx.de
License: Apache License 2.0
Keywords: members membership fees club group clubs associations association
Classifier: Development Status :: 5 - Production/Stable
Classifier: Environment :: Web Environment
Classifier: Framework :: Django
Classifier: Framework :: Django :: 3.2
Classifier: Intended Audience :: Developers
Classifier: Intended Audience :: Other Audience
Classifier: License :: OSI Approved
Classifier: License :: OSI Approved :: Apache Software License
Classifier: Programming Language :: Python :: 3
Classifier: Programming Language :: Python :: 3.8
Classifier: Programming Language :: Python :: 3.9
Classifier: Programming Language :: Python :: 3.10
Classifier: Topic :: Internet :: WWW/HTTP :: Dynamic Content
Requires-Python: >=3.8
Requires-Dist: canonicaljson ==2.0.0
Requires-Dist: celery <6.0,>=5.1
Requires-Dist: chardet <5.3,>=4.0
Requires-Dist: csscompressor ~=0.9.5
Requires-Dist: dateparser <1.2,>=1.1
Requires-Dist: django-annoying ~=0.10.0
Requires-Dist: django-bootstrap4 <23.3,>=3.0
Requires-Dist: django-compressor <5.0,>=2.4
Requires-Dist: django-extensions <3.3,>=3.1
Requires-Dist: django-formset-js-improved ==0.5.0.3
Requires-Dist: django-i18nfield <1.10,>=1.9
Requires-Dist: django-libsass <0.10,>=0.8
Requires-Dist: django-localflavor <4.1,>=3.0
Requires-Dist: django-select2 <8.2,>=7.7
Requires-Dist: django-solo ==2.1.*
Requires-Dist: Django <3.3,>=3.2
Requires-Dist: inlinestyler ~=0.2
Requires-Dist: jinja2 >=2.10.1
Requires-Dist: more-itertools <10.2,>=8.10
Requires-Dist: psycopg2-binary
Requires-Dist: pynacl <1.6,>=1.4
Requires-Dist: python-dateutil
Requires-Dist: python-magic ~=0.4.0
Requires-Dist: qrcode[pil] <7.5,>=7.3
Requires-Dist: schwifty ==2023.6.0
Requires-Dist: unicodecsv ~=0.14.0
Requires-Dist: whitenoise <6.6,>=6.4
Provides-Extra: dev
Requires-Dist: black ; extra == 'dev'
Requires-Dist: check-manifest ; extra == 'dev'
Requires-Dist: djhtml ; extra == 'dev'
Requires-Dist: flake8 ; extra == 'dev'
Requires-Dist: flake8-bugbear ; extra == 'dev'
Requires-Dist: freezegun ; extra == 'dev'
Requires-Dist: isort ; extra == 'dev'
Requires-Dist: ipython ; extra == 'dev'
Requires-Dist: pytest ; extra == 'dev'
Requires-Dist: pytest-cov ; extra == 'dev'
Requires-Dist: pytest-django ; extra == 'dev'
Requires-Dist: pytest-rerunfailures ; extra == 'dev'
Requires-Dist: pytest-sugar ; extra == 'dev'
Requires-Dist: pytest-xdist ; extra == 'dev'
Provides-Extra: mysql
Requires-Dist: mysqlclient ; extra == 'mysql'
Provides-Extra: postgres
Requires-Dist: psycopg2-binary ; extra == 'postgres'
